Metadata-Version: 2.1
Name: pdfzipcracker
Version: 1.0
Classifier: Programming Language :: Python :: 3
Classifier: License :: OSI Approved :: MIT License
Classifier: Operating System :: OS Independent
Requires-Python: >=3.6
Requires-Dist: PyPDF2
Requires-Dist: pyzipper
